setup.py
distributions_probability/Binomialdistribution.py
distributions_probability/Gaussiandistribution.py
distributions_probability/Generaldistribution.py
distributions_probability/__init__.py
distributions_probability.egg-info/PKG-INFO
distributions_probability.egg-info/SOURCES.txt
distributions_probability.egg-info/dependency_links.txt
distributions_probability.egg-info/not-zip-safe
distributions_probability.egg-info/top_level.txt