Metadata-Version: 1.0
Name: distributions-probability
Version: 0.1
Summary: Gaussian and Binomial distributions
Home-page: UNKNOWN
Author: Payal Kamboj
Author-email: UNKNOWN
License: UNKNOWN
Platform: UNKNOWN
